Workbook

Sheet Cover
A1: Chhat: the independent AI solar advisor for Indian homes
A2: Five-year financial model, base case. Prepared by Claude (AI) for the HackIndia AI-First Startup Hackathon, Oct 2026.
A4: How to read this model
A5: Blue text | B5: Hard-coded input. Change these.
A6: Black text | B6: Formula. Don't overwrite.
A7: Green text | B7: Link to another sheet.
A8: Yellow fill | B8: Key lever with the largest effect on the outcome.
A9: FY27* | B9: Part year: Nov 2026 to Mar 2027 (5 months).
A10: Units | B10: ₹ lakh unless a row says otherwise. 1 crore = 100 lakh.
A12: Sheets
A13: Assumptions | B13: Every input, with its source or rationale.
A14: Revenue | B14: Funnel and five revenue streams.
A15: P&L | B15: Revenue, costs, EBITDA, tax, PAT.
A16: Cash | B16: Funding, burn, runway.
A17: Unit economics | B17: Per report and per installed home.
A18: Market | B18: TAM / SAM / SOM.
A19: Sensitivity | B19: FY29 EBITDA vs lead fee and lead-to-install conversion.

Sheet Assumptions
A1: Assumptions
A3: Input | B3: Unit / note | C3: FY27* | D3: FY28 | E3: FY29 | F3: FY30 | G3: FY31 | I3: Source / rationale
A4: Months in year | B4: FY27 is a part year from launch in Nov 2026 | C4: 5 | D4: 12 | E4: 12 | F4: 12 | G4: 12
A5: Roof Reports generated | B5: count; organic + WhatsApp shares + paid search | C5: 40000 | D5: 400000 | E5: 1200000 | F5: 2500000 | G5: 4000000 | I5: Plan assumption. FY31 = 40 lakh reports, against ~45 lakh residential installs a year nationally (PM Surya Ghar pace: 16,328/day in Jul 2026, DD India).
A6: Report → verified lead | B6: % of reports that ask for vetted installer quotes | C6: 0.08 | D6: 0.08 | E6: 0.08 | F6: 0.08 | G6: 0.08 | I6: Assumption. Comparable intent marketplaces convert 5-12% of tool users to leads.
A7: Verified lead → installed home | B7: % | C7: 0.2 | D7: 0.2 | E7: 0.2 | F7: 0.2 | G7: 0.2 | I7: Assumption. Pre-qualified leads with a bill and roof model close better than cold leads (industry 8-15%).
A8: Lead fee paid by installer | B8: ₹ per verified lead | C8: 1500 | D8: 1500 | E8: 1500 | F8: 1500 | G8: 1500 | I8: Assumption. Indian solar leads trade at ₹300-1,500 unverified; verified, sized leads at the top of that range.
A9: Average system size | B9: kWp | C9: 3.2 | D9: 3.2 | E9: 3.2 | F9: 3.2 | G9: 3.2 | I9: Most PM Surya Ghar homes install ~3 kW to capture the full ₹78,000 subsidy.
A10: Average installed price | B10: ₹ per kW | C10: 58000 | D10: 57000 | E10: 56000 | F10: 55000 | G10: 54000 | I10: Chhat fair-price band, Oct 2026, falling ~2%/yr. Sources: Avaada, VoltFlow, installer lists.
A11: Success fee on completed installs | B11: % of system value | C11: 0.02 | D11: 0.02 | E11: 0.02 | F11: 0.02 | G11: 0.02 | I11: Assumption, paid by installer on commissioning.
A12: Installs financed | B12: % of installs | C12: 0.35 | D12: 0.35 | E12: 0.35 | F12: 0.35 | G12: 0.35 | I12: Assumption. PM Surya Ghar collateral-free loans up to ₹2 lakh at repo + 0.5%.
A13: Average loan | B13: ₹ | C13: 160000 | D13: 160000 | E13: 160000 | F13: 160000 | G13: 160000 | I13: ≈ 90% of a 3 kW system before subsidy.
A14: Loan origination fee | B14: % of loan | C14: 0.01 | D14: 0.01 | E14: 0.01 | F14: 0.01 | G14: 0.01 | I14: Typical DSA payout from banks/NBFCs for small-ticket retail loans.
A15: Paying installers on SaaS (average) | B15: count | C15: 25 | D15: 300 | E15: 900 | F15: 1600 | G15: 2500 | I15: India has 10,000+ registered rooftop vendors on the national portal (assumption).
A16: Installer SaaS price | B16: ₹ per month | C16: 2999 | D16: 2999 | E16: 2999 | F16: 2999 | G16: 2999
A17: State / DISCOM analytics contracts | B17: count | C17: 0 | D17: 1 | E17: 3 | F17: 6 | G17: 10 | I17: B2G sales: billing-error heatmaps, net-meter backlog, subsidy funnel.
A18: Contract value | B18: ₹ lakh per state per year | C18: 40 | D18: 40 | E18: 40 | F18: 40 | G18: 40
A19: Blended acquisition cost | B19: ₹ per report | C19: 100 | D19: 85 | E19: 75 | F19: 65 | G19: 60 | I19: Paid search + content + referral. Falls slowly as shares and SEO compound; kept high for caution.
A20: AI + infrastructure cost | B20: ₹ per report | C20: 6 | D20: 5 | E20: 4 | F20: 3.5 | G20: 3 | I20: Claude Opus 5.5 at $4/$20 per MTok: ~2 extraction calls + chat ≈ ₹5. Falls with caching and routing.
A21: Team size (average) | B21: people | C21: 10 | D21: 35 | E21: 70 | F21: 110 | G21: 150 | I21: Product/eng, growth, installer ops, lead-verification callers, B2G sales.
A22: Loaded cost per person | B22: ₹ lakh per year | C22: 15 | D22: 15 | E22: 15 | F22: 15 | G22: 15 | I22: Blended Indian startup CTC incl. benefits.
A23: G&A | B23: % of payroll | C23: 0.15 | D23: 0.15 | E23: 0.15 | F23: 0.15 | G23: 0.15
A24: Tools, office, compliance | B24: ₹ lakh per year | C24: 10 | D24: 50 | E24: 100 | F24: 150 | G24: 200
A25: Payments + partner ops | B25: % of revenue | C25: 0.03 | D25: 0.03 | E25: 0.03 | F25: 0.03 | G25: 0.03
A26: Corporate tax rate | B26: % of positive PBT | C26: 0.2517 | D26: 0.2517 | E26: 0.2517 | F26: 0.2517 | G26: 0.2517 | I26: Section 115BAA base rate incl. surcharge and cess. Losses not carried forward here (conservative).
A27: Equity raised | B27: ₹ lakh | C27: 600 | D27: 0 | E27: 4000 | F27: 0 | G27: 0 | I27: Seed ₹6 crore at launch; Series A ₹40 crore in FY29 (assumption).
A28: Opening cash | B28: ₹ lakh | C28: 20 | I28: Founders' capital.

Sheet Revenue
A1: Revenue build
A3: ₹ lakh unless stated | B3: Unit / note | C3: FY27* | D3: FY28 | E3: FY29 | F3: FY30 | G3: FY31
A4: Reports generated | B4: count | C4: =Assumptions!C$5 -> 40000 | D4: =Assumptions!D$5 -> 400000 | E4: =Assumptions!E$5 -> 1200000 | F4: =Assumptions!F$5 -> 2500000 | G4: =Assumptions!G$5 -> 4000000
A5: Verified leads | B5: count | C5: =C4*Assumptions!C$6 -> 3200 | D5: =D4*Assumptions!D$6 -> 32000 | E5: =E4*Assumptions!E$6 -> 96000 | F5: =F4*Assumptions!F$6 -> 200000 | G5: =G4*Assumptions!G$6 -> 320000
A6: Installed homes | B6: count | C6: =C5*Assumptions!C$7 -> 640 | D6: =D5*Assumptions!D$7 -> 6400 | E6: =E5*Assumptions!E$7 -> 19200 | F6: =F5*Assumptions!F$7 -> 40000 | G6: =G5*Assumptions!G$7 -> 64000
A7: Average system value | B7: ₹ | C7: =Assumptions!C$9*Assumptions!C$10 -> 185600 | D7: =Assumptions!D$9*Assumptions!D$10 -> 182400 | E7: =Assumptions!E$9*Assumptions!E$10 -> 179200 | F7: =Assumptions!F$9*Assumptions!F$10 -> 176000 | G7: =Assumptions!G$9*Assumptions!G$10 -> 172800
A8: Financed installs | B8: count | C8: =C6*Assumptions!C$12 -> 224 | D8: =D6*Assumptions!D$12 -> 2240 | E8: =E6*Assumptions!E$12 -> 6720 | F8: =F6*Assumptions!F$12 -> 14000 | G8: =G6*Assumptions!G$12 -> 22400
A10: Lead fees | B10: ₹ lakh | C10: =C5*Assumptions!C$8/100000 -> 48 | D10: =D5*Assumptions!D$8/100000 -> 480 | E10: =E5*Assumptions!E$8/100000 -> 1440 | F10: =F5*Assumptions!F$8/100000 -> 3000 | G10: =G5*Assumptions!G$8/100000 -> 4800
A11: Success fees | B11: ₹ lakh | C11: =C6*C7*Assumptions!C$11/100000 -> 23.7568 | D11: =D6*D7*Assumptions!D$11/100000 -> 233.472 | E11: =E6*E7*Assumptions!E$11/100000 -> 688.128 | F11: =F6*F7*Assumptions!F$11/100000 -> 1408 | G11: =G6*G7*Assumptions!G$11/100000 -> 2211.84
A12: Loan origination | B12: ₹ lakh | C12: =C8*Assumptions!C$13*Assumptions!C$14/100000 -> 3.584 | D12: =D8*Assumptions!D$13*Assumptions!D$14/100000 -> 35.84 | E12: =E8*Assumptions!E$13*Assumptions!E$14/100000 -> 107.52 | F12: =F8*Assumptions!F$13*Assumptions!F$14/100000 -> 224 | G12: =G8*Assumptions!G$13*Assumptions!G$14/100000 -> 358.4
A13: Installer SaaS | B13: ₹ lakh | C13: =Assumptions!C$15*Assumptions!C$16*Assumptions!C$4/100000 -> 3.74875 | D13: =Assumptions!D$15*Assumptions!D$16*Assumptions!D$4/100000 -> 107.964 | E13: =Assumptions!E$15*Assumptions!E$16*Assumptions!E$4/100000 -> 323.892 | F13: =Assumptions!F$15*Assumptions!F$16*Assumptions!F$4/100000 -> 575.808 | G13: =Assumptions!G$15*Assumptions!G$16*Assumptions!G$4/100000 -> 899.7
A14: DISCOM / state analytics | B14: ₹ lakh | C14: =Assumptions!C$17*Assumptions!C$18*Assumptions!C$4/12 -> 0 | D14: =Assumptions!D$17*Assumptions!D$18*Assumptions!D$4/12 -> 40 | E14: =Assumptions!E$17*Assumptions!E$18*Assumptions!E$4/12 -> 120 | F14: =Assumptions!F$17*Assumptions!F$18*Assumptions!F$4/12 -> 240 | G14: =Assumptions!G$17*Assumptions!G$18*Assumptions!G$4/12 -> 400
A15: Total revenue | B15: ₹ lakh | C15: =SUM(C10:C14) -> 79.08955 | D15: =SUM(D10:D14) -> 897.276 | E15: =SUM(E10:E14) -> 2679.54 | F15: =SUM(F10:F14) -> 5447.808 | G15: =SUM(G10:G14) -> 8669.94
A16: Growth | B16: % y/y | D16: =IF(C15=0,0,D15/C15-1) -> 10.345064 | E16: =IF(D15=0,0,E15/D15-1) -> 1.9863052 | F16: =IF(E15=0,0,F15/E15-1) -> 1.0331131 | G16: =IF(F15=0,0,G15/F15-1) -> 0.59145476
A17: Marketplace share of revenue | B17: % | C17: =IF(C15=0,0,SUM(C10:C12)/C15) -> 0.9526012 | D17: =IF(D15=0,0,SUM(D10:D12)/D15) -> 0.83509645 | E17: =IF(E15=0,0,SUM(E10:E12)/E15) -> 0.83434022 | F17: =IF(F15=0,0,SUM(F10:F12)/F15) -> 0.85025023 | G17: =IF(G15=0,0,SUM(G10:G12)/G15) -> 0.85009123

Sheet P&L
A1: Profit and loss
A3: ₹ lakh unless stated | B3: Unit / note | C3: FY27* | D3: FY28 | E3: FY29 | F3: FY30 | G3: FY31
A4: Revenue | C4: =Revenue!C15 -> 79.08955 | D4: =Revenue!D15 -> 897.276 | E4: =Revenue!E15 -> 2679.54 | F4: =Revenue!F15 -> 5447.808 | G4: =Revenue!G15 -> 8669.94
A6: Customer acquisition | C6: =Assumptions!C$5*Assumptions!C$19/100000 -> 40 | D6: =Assumptions!D$5*Assumptions!D$19/100000 -> 340 | E6: =Assumptions!E$5*Assumptions!E$19/100000 -> 900 | F6: =Assumptions!F$5*Assumptions!F$19/100000 -> 1625 | G6: =Assumptions!G$5*Assumptions!G$19/100000 -> 2400
A7: AI + infrastructure | C7: =Assumptions!C$5*Assumptions!C$20/100000 -> 2.4 | D7: =Assumptions!D$5*Assumptions!D$20/100000 -> 20 | E7: =Assumptions!E$5*Assumptions!E$20/100000 -> 48 | F7: =Assumptions!F$5*Assumptions!F$20/100000 -> 87.5 | G7: =Assumptions!G$5*Assumptions!G$20/100000 -> 120
A8: Payments + partner ops | C8: =C4*Assumptions!C$25 -> 2.3726865 | D8: =D4*Assumptions!D$25 -> 26.91828 | E8: =E4*Assumptions!E$25 -> 80.3862 | F8: =F4*Assumptions!F$25 -> 163.43424 | G8: =G4*Assumptions!G$25 -> 260.0982
A9: Gross profit | C9: =C4-SUM(C6:C8) -> 34.316863 | D9: =D4-SUM(D6:D8) -> 510.35772 | E9: =E4-SUM(E6:E8) -> 1651.1538 | F9: =F4-SUM(F6:F8) -> 3571.8738 | G9: =G4-SUM(G6:G8) -> 5889.8418
A10: Gross margin | C10: =IF(C4=0,0,C9/C4) -> 0.43389883 | D10: =IF(D4=0,0,D9/D4) -> 0.56878566 | E10: =IF(E4=0,0,E9/E4) -> 0.61620793 | F10: =IF(F4=0,0,F9/F4) -> 0.65565339 | G10: =IF(G4=0,0,G9/G4) -> 0.67934055
A12: Payroll | C12: =Assumptions!C$21*Assumptions!C$22*Assumptions!C$4/12 -> 62.5 | D12: =Assumptions!D$21*Assumptions!D$22*Assumptions!D$4/12 -> 525 | E12: =Assumptions!E$21*Assumptions!E$22*Assumptions!E$4/12 -> 1050 | F12: =Assumptions!F$21*Assumptions!F$22*Assumptions!F$4/12 -> 1650 | G12: =Assumptions!G$21*Assumptions!G$22*Assumptions!G$4/12 -> 2250
A13: G&A | C13: =C12*Assumptions!C$23 -> 9.375 | D13: =D12*Assumptions!D$23 -> 78.75 | E13: =E12*Assumptions!E$23 -> 157.5 | F13: =F12*Assumptions!F$23 -> 247.5 | G13: =G12*Assumptions!G$23 -> 337.5
A14: Tools, office, compliance | C14: =Assumptions!C$24 -> 10 | D14: =Assumptions!D$24 -> 50 | E14: =Assumptions!E$24 -> 100 | F14: =Assumptions!F$24 -> 150 | G14: =Assumptions!G$24 -> 200
A15: Total operating expenses | C15: =SUM(C12:C14) -> 81.875 | D15: =SUM(D12:D14) -> 653.75 | E15: =SUM(E12:E14) -> 1307.5 | F15: =SUM(F12:F14) -> 2047.5 | G15: =SUM(G12:G14) -> 2787.5
A17: EBITDA | C17: =C9-C15 -> -47.558137 | D17: =D9-D15 -> -143.39228 | E17: =E9-E15 -> 343.6538 | F17: =F9-F15 -> 1524.3738 | G17: =G9-G15 -> 3102.3418
A18: EBITDA margin | C18: =IF(C4=0,0,C17/C4) -> -0.6013201 | D18: =IF(D4=0,0,D17/D4) -> -0.15980844 | E18: =IF(E4=0,0,E17/E4) -> 0.12825104 | F18: =IF(F4=0,0,F17/F4) -> 0.27981415 | G18: =IF(G4=0,0,G17/G4) -> 0.35782737
A19: Tax | C19: =MAX(0,C17)*Assumptions!C$26 -> 0 | D19: =MAX(0,D17)*Assumptions!D$26 -> 0 | E19: =MAX(0,E17)*Assumptions!E$26 -> 86.497661 | F19: =MAX(0,F17)*Assumptions!F$26 -> 383.68488 | G19: =MAX(0,G17)*Assumptions!G$26 -> 780.85943
A20: Profit after tax | C20: =C17-C19 -> -47.558137 | D20: =D17-D19 -> -143.39228 | E20: =E17-E19 -> 257.15614 | F20: =F17-F19 -> 1140.6889 | G20: =G17-G19 -> 2321.4824
A21: Revenue (₹ crore) | C21: =C4/100 -> 0.7908955 | D21: =D4/100 -> 8.97276 | E21: =E4/100 -> 26.7954 | F21: =F4/100 -> 54.47808 | G21: =G4/100 -> 86.6994
A22: EBITDA (₹ crore) | C22: =C17/100 -> -0.47558136 | D22: =D17/100 -> -1.4339228 | E22: =E17/100 -> 3.436538 | F22: =F17/100 -> 15.243738 | G22: =G17/100 -> 31.023418

Sheet Cash
A1: Cash and runway
A3: ₹ lakh unless stated | B3: Unit / note | C3: FY27* | D3: FY28 | E3: FY29 | F3: FY30 | G3: FY31
A4: Opening cash | C4: =Assumptions!C$28 -> 20 | D4: =C9 -> 567.44186 | E4: =D9 -> 382.04958 | F4: =E9 -> 4555.2057 | G4: =F9 -> 5563.8946
A5: Equity raised | C5: =Assumptions!C$27 -> 600 | D5: =Assumptions!D$27 -> 0 | E5: =Assumptions!E$27 -> 4000 | F5: =Assumptions!F$27 -> 0 | G5: =Assumptions!G$27 -> 0
A6: EBITDA | C6: ='P&L'!C17 -> -47.558137 | D6: ='P&L'!D17 -> -143.39228 | E6: ='P&L'!E17 -> 343.6538 | F6: ='P&L'!F17 -> 1524.3738 | G6: ='P&L'!G17 -> 3102.3418
A7: Tax paid | C7: =-'P&L'!C19 -> 0 | D7: =-'P&L'!D19 -> 0 | E7: =-'P&L'!E19 -> -86.497661 | F7: =-'P&L'!F19 -> -383.68488 | G7: =-'P&L'!G19 -> -780.85943
A8: Capex (laptops, devices) | B8: ₹1.2 lakh per head | C8: =-Assumptions!C$21*1.2*Assumptions!C$4/12 -> -5 | D8: =-Assumptions!D$21*1.2*Assumptions!D$4/12 -> -42 | E8: =-Assumptions!E$21*1.2*Assumptions!E$4/12 -> -84 | F8: =-Assumptions!F$21*1.2*Assumptions!F$4/12 -> -132 | G8: =-Assumptions!G$21*1.2*Assumptions!G$4/12 -> -180
A9: Closing cash | C9: =SUM(C4:C8) -> 567.44186 | D9: =SUM(D4:D8) -> 382.04958 | E9: =SUM(E4:E8) -> 4555.2057 | F9: =SUM(F4:F8) -> 5563.8946 | G9: =SUM(G4:G8) -> 7705.377
A10: Monthly net burn (if negative) | C10: =IF((C6+C7+C8)<0,-(C6+C7+C8)/Assumptions!C$4,0) -> 10.511627 | D10: =IF((D6+D7+D8)<0,-(D6+D7+D8)/Assumptions!D$4,0) -> 15.449357 | E10: =IF((E6+E7+E8)<0,-(E6+E7+E8)/Assumptions!E$4,0) -> 0 | F10: =IF((F6+F7+F8)<0,-(F6+F7+F8)/Assumptions!F$4,0) -> 0 | G10: =IF((G6+G7+G8)<0,-(G6+G7+G8)/Assumptions!G$4,0) -> 0
A11: Runway at that burn | C11: =IF(C10=0,"cash positive",C9/C10) -> 53.982304 | D11: =IF(D10=0,"cash positive",D9/D10) -> 24.729158 | E11: =IF(E10=0,"cash positive",E9/E10) -> cash positive | F11: =IF(F10=0,"cash positive",F9/F10) -> cash positive | G11: =IF(G10=0,"cash positive",G9/G10) -> cash positive
A13: Funding ask
A14: Seed round | B14: ₹ lakh | C14: =Assumptions!C$27 -> 600
A15: Equity offered | C15: 0.15
A16: Implied post-money valuation | B16: ₹ lakh | C16: =C14/C15 -> 4000
A17: Lowest closing cash, FY27-FY31 | B17: ₹ lakh | C17: =MIN(C9:G9) -> 382.04958
A18: Use of funds | D18: ₹ lakh
A19: Product & engineering | C19: 0.45 | D19: =C19*$C$14 -> 270
A20: Growth (content, referral, paid search) | C20: 0.3 | D20: =C20*$C$14 -> 180
A21: Installer network & lead verification | C21: 0.15 | D21: =C21*$C$14 -> 90
A22: Compliance, legal, G&A | C22: 0.1 | D22: =C22*$C$14 -> 60
C23: =SUM(C19:C22) -> 1

Sheet Unit economics
A1: Unit economics (FY28 base)
A2: Metric | B2: Value | C2: Unit
A3: Revenue per report | B3: =Revenue!D15*100000/Revenue!D4 -> 224.319 | C3: ₹
A4: Variable cost per report (CAC + AI) | B4: =Assumptions!D$19+Assumptions!D$20 -> 90 | C4: ₹
A5: Contribution per report | B5: =B3-B4 -> 134.319 | C5: ₹
A6: Revenue to variable cost | B6: =IF(B4=0,0,B3/B4) -> 2.4924333 | C6: x
A8: Reports needed per installed home | B8: =1/(Assumptions!D$6*Assumptions!D$7) -> 62.5 | C8: count
A9: Marketplace revenue per installed home | B9: =SUM(Revenue!D10:D12)*100000/Revenue!D6 -> 11708 | C9: ₹
A10: Variable cost per installed home | B10: =B8*B4 -> 5625 | C10: ₹
A11: Contribution per installed home | B11: =B9-B10 -> 6083 | C11: ₹
A12: Contribution margin | B12: =IF(B9=0,0,B11/B9) -> 0.51955928 | C12: %
A14: Homeowner's saving, 3 kW in Delhi (year 1) | B14: 28869 | C14: ₹ | D14: Chhat Roof Report output for Delhi, 450 units in May (see app). Source: Chhat engine, NASA POWER.
A15: Chhat's take as share of the home's 25-yr savings | B15: =B9/(B14*25) -> 0.016222245 | C15: %

Sheet Market
A1: Market sizing
A3: Homes still to reach the PM Surya Ghar target (1 crore − ~51 lakh) | B3: 49 | C3: lakh homes | D3: DD India / MNRE, Sep 2026
A4: Average system value | B4: =Assumptions!D$9*Assumptions!D$10 -> 182400 | C4: ₹
A5: Installation value in the scheme window | B5: =B3*100000*B4/10000000 -> 89376 | C5: ₹ crore
A6: Economic residential rooftop potential (with subsidy) | B6: 32 | C6: GW | D6: CEEW 2023: 637 GW technical, 118 GW after consumption, 32 GW economic
A7: Homes in that potential at 3.2 kW | B7: =B6*1000000/Assumptions!D$9/100000 -> 100 | C7: lakh homes
A8: TAM: installation value of economic potential | B8: =B7*100000*B4/10000000 -> 182400 | C8: ₹ crore
A9: Chhat take rate on an installed home (marketplace) | B9: ='Unit economics'!B9/B4 -> 0.064188596 | C9: % of system value
A10: SAM: Chhat revenue pool on the TAM | B10: =B8*B9 -> 11708 | C10: ₹ crore
A11: SOM: FY31 revenue | B11: ='P&L'!G21 -> 86.6994 | C11: ₹ crore
A12: SOM as share of SAM | B12: =IF(B10=0,0,B11/B10) -> 0.0074051418 | C12: %

Sheet Sensitivity
A1: FY29 EBITDA (₹ lakh) vs lead fee and lead → install conversion
A3: Lead → install ↓ / Lead fee (₹) → | B3: 900 | C3: 1200 | D3: 1500 | E3: 1800 | F3: 2100
A4: 0.12 | B4: =((Assumptions!E$5*Assumptions!E$6*B$3+Assumptions!E$5*Assumptions!E$6*$A4*Assumptions!E$9*Assumptions!E$10*Assumptions!E$11+Assumptions!E$5*Assumptions!E$6*$A4*Assumptions!E$12*Assumptions!E$13*Assumptions!E$14)/100000+Revenue!E13+Revenue!E14)*(1-Assumptions!E$25)-'P&L'!E6-'P&L'!E7-'P&L'!E15 -> -523.77762 | C4: =((Assumptions!E$5*Assumptions!E$6*C$3+Assumptions!E$5*Assumptions!E$6*$A4*Assumptions!E$9*Assumptions!E$10*Assumptions!E$11+Assumptions!E$5*Assumptions!E$6*$A4*Assumptions!E$12*Assumptions!E$13*Assumptions!E$14)/100000+Revenue!E13+Revenue!E14)*(1-Assumptions!E$25)-'P&L'!E6-'P&L'!E7-'P&L'!E15 -> -244.41762 | D4: =((Assumptions!E$5*Assumptions!E$6*D$3+Assumptions!E$5*Assumptions!E$6*$A4*Assumptions!E$9*Assumptions!E$10*Assumptions!E$11+Assumptions!E$5*Assumptions!E$6*$A4*Assumptions!E$12*Assumptions!E$13*Assumptions!E$14)/100000+Revenue!E13+Revenue!E14)*(1-Assumptions!E$25)-'P&L'!E6-'P&L'!E7-'P&L'!E15 -> 34.942376 | E4: =((Assumptions!E$5*Assumptions!E$6*E$3+Assumptions!E$5*Assumptions!E$6*$A4*Assumptions!E$9*Assumptions!E$10*Assumptions!E$11+Assumptions!E$5*Assumptions!E$6*$A4*Assumptions!E$12*Assumptions!E$13*Assumptions!E$14)/100000+Revenue!E13+Revenue!E14)*(1-Assumptions!E$25)-'P&L'!E6-'P&L'!E7-'P&L'!E15 -> 314.30238 | F4: =((Assumptions!E$5*Assumptions!E$6*F$3+Assumptions!E$5*Assumptions!E$6*$A4*Assumptions!E$9*Assumptions!E$10*Assumptions!E$11+Assumptions!E$5*Assumptions!E$6*$A4*Assumptions!E$12*Assumptions!E$13*Assumptions!E$14)/100000+Revenue!E13+Revenue!E14)*(1-Assumptions!E$25)-'P&L'!E6-'P&L'!E7-'P&L'!E15 -> 593.66238
A5: 0.16 | B5: =((Assumptions!E$5*Assumptions!E$6*B$3+Assumptions!E$5*Assumptions!E$6*$A5*Assumptions!E$9*Assumptions!E$10*Assumptions!E$11+Assumptions!E$5*Assumptions!E$6*$A5*Assumptions!E$12*Assumptions!E$13*Assumptions!E$14)/100000+Revenue!E13+Revenue!E14)*(1-Assumptions!E$25)-'P&L'!E6-'P&L'!E7-'P&L'!E15 -> -369.42191 | C5: =((Assumptions!E$5*Assumptions!E$6*C$3+Assumptions!E$5*Assumptions!E$6*$A5*Assumptions!E$9*Assumptions!E$10*Assumptions!E$11+Assumptions!E$5*Assumptions!E$6*$A5*Assumptions!E$12*Assumptions!E$13*Assumptions!E$14)/100000+Revenue!E13+Revenue!E14)*(1-Assumptions!E$25)-'P&L'!E6-'P&L'!E7-'P&L'!E15 -> -90.061912 | D5: =((Assumptions!E$5*Assumptions!E$6*D$3+Assumptions!E$5*Assumptions!E$6*$A5*Assumptions!E$9*Assumptions!E$10*Assumptions!E$11+Assumptions!E$5*Assumptions!E$6*$A5*Assumptions!E$12*Assumptions!E$13*Assumptions!E$14)/100000+Revenue!E13+Revenue!E14)*(1-Assumptions!E$25)-'P&L'!E6-'P&L'!E7-'P&L'!E15 -> 189.29809 | E5: =((Assumptions!E$5*Assumptions!E$6*E$3+Assumptions!E$5*Assumptions!E$6*$A5*Assumptions!E$9*Assumptions!E$10*Assumptions!E$11+Assumptions!E$5*Assumptions!E$6*$A5*Assumptions!E$12*Assumptions!E$13*Assumptions!E$14)/100000+Revenue!E13+Revenue!E14)*(1-Assumptions!E$25)-'P&L'!E6-'P&L'!E7-'P&L'!E15 -> 468.65809 | F5: =((Assumptions!E$5*Assumptions!E$6*F$3+Assumptions!E$5*Assumptions!E$6*$A5*Assumptions!E$9*Assumptions!E$10*Assumptions!E$11+Assumptions!E$5*Assumptions!E$6*$A5*Assumptions!E$12*Assumptions!E$13*Assumptions!E$14)/100000+Revenue!E13+Revenue!E14)*(1-Assumptions!E$25)-'P&L'!E6-'P&L'!E7-'P&L'!E15 -> 748.01809
A6: 0.2 | B6: =((Assumptions!E$5*Assumptions!E$6*B$3+Assumptions!E$5*Assumptions!E$6*$A6*Assumptions!E$9*Assumptions!E$10*Assumptions!E$11+Assumptions!E$5*Assumptions!E$6*$A6*Assumptions!E$12*Assumptions!E$13*Assumptions!E$14)/100000+Revenue!E13+Revenue!E14)*(1-Assumptions!E$25)-'P&L'!E6-'P&L'!E7-'P&L'!E15 -> -215.0662 | C6: =((Assumptions!E$5*Assumptions!E$6*C$3+Assumptions!E$5*Assumptions!E$6*$A6*Assumptions!E$9*Assumptions!E$10*Assumptions!E$11+Assumptions!E$5*Assumptions!E$6*$A6*Assumptions!E$12*Assumptions!E$13*Assumptions!E$14)/100000+Revenue!E13+Revenue!E14)*(1-Assumptions!E$25)-'P&L'!E6-'P&L'!E7-'P&L'!E15 -> 64.2938 | D6: =((Assumptions!E$5*Assumptions!E$6*D$3+Assumptions!E$5*Assumptions!E$6*$A6*Assumptions!E$9*Assumptions!E$10*Assumptions!E$11+Assumptions!E$5*Assumptions!E$6*$A6*Assumptions!E$12*Assumptions!E$13*Assumptions!E$14)/100000+Revenue!E13+Revenue!E14)*(1-Assumptions!E$25)-'P&L'!E6-'P&L'!E7-'P&L'!E15 -> 343.6538 | E6: =((Assumptions!E$5*Assumptions!E$6*E$3+Assumptions!E$5*Assumptions!E$6*$A6*Assumptions!E$9*Assumptions!E$10*Assumptions!E$11+Assumptions!E$5*Assumptions!E$6*$A6*Assumptions!E$12*Assumptions!E$13*Assumptions!E$14)/100000+Revenue!E13+Revenue!E14)*(1-Assumptions!E$25)-'P&L'!E6-'P&L'!E7-'P&L'!E15 -> 623.0138 | F6: =((Assumptions!E$5*Assumptions!E$6*F$3+Assumptions!E$5*Assumptions!E$6*$A6*Assumptions!E$9*Assumptions!E$10*Assumptions!E$11+Assumptions!E$5*Assumptions!E$6*$A6*Assumptions!E$12*Assumptions!E$13*Assumptions!E$14)/100000+Revenue!E13+Revenue!E14)*(1-Assumptions!E$25)-'P&L'!E6-'P&L'!E7-'P&L'!E15 -> 902.3738
A7: 0.24 | B7: =((Assumptions!E$5*Assumptions!E$6*B$3+Assumptions!E$5*Assumptions!E$6*$A7*Assumptions!E$9*Assumptions!E$10*Assumptions!E$11+Assumptions!E$5*Assumptions!E$6*$A7*Assumptions!E$12*Assumptions!E$13*Assumptions!E$14)/100000+Revenue!E13+Revenue!E14)*(1-Assumptions!E$25)-'P&L'!E6-'P&L'!E7-'P&L'!E15 -> -60.710488 | C7: =((Assumptions!E$5*Assumptions!E$6*C$3+Assumptions!E$5*Assumptions!E$6*$A7*Assumptions!E$9*Assumptions!E$10*Assumptions!E$11+Assumptions!E$5*Assumptions!E$6*$A7*Assumptions!E$12*Assumptions!E$13*Assumptions!E$14)/100000+Revenue!E13+Revenue!E14)*(1-Assumptions!E$25)-'P&L'!E6-'P&L'!E7-'P&L'!E15 -> 218.64951 | D7: =((Assumptions!E$5*Assumptions!E$6*D$3+Assumptions!E$5*Assumptions!E$6*$A7*Assumptions!E$9*Assumptions!E$10*Assumptions!E$11+Assumptions!E$5*Assumptions!E$6*$A7*Assumptions!E$12*Assumptions!E$13*Assumptions!E$14)/100000+Revenue!E13+Revenue!E14)*(1-Assumptions!E$25)-'P&L'!E6-'P&L'!E7-'P&L'!E15 -> 498.00951 | E7: =((Assumptions!E$5*Assumptions!E$6*E$3+Assumptions!E$5*Assumptions!E$6*$A7*Assumptions!E$9*Assumptions!E$10*Assumptions!E$11+Assumptions!E$5*Assumptions!E$6*$A7*Assumptions!E$12*Assumptions!E$13*Assumptions!E$14)/100000+Revenue!E13+Revenue!E14)*(1-Assumptions!E$25)-'P&L'!E6-'P&L'!E7-'P&L'!E15 -> 777.36951 | F7: =((Assumptions!E$5*Assumptions!E$6*F$3+Assumptions!E$5*Assumptions!E$6*$A7*Assumptions!E$9*Assumptions!E$10*Assumptions!E$11+Assumptions!E$5*Assumptions!E$6*$A7*Assumptions!E$12*Assumptions!E$13*Assumptions!E$14)/100000+Revenue!E13+Revenue!E14)*(1-Assumptions!E$25)-'P&L'!E6-'P&L'!E7-'P&L'!E15 -> 1056.7295
A8: 0.28 | B8: =((Assumptions!E$5*Assumptions!E$6*B$3+Assumptions!E$5*Assumptions!E$6*$A8*Assumptions!E$9*Assumptions!E$10*Assumptions!E$11+Assumptions!E$5*Assumptions!E$6*$A8*Assumptions!E$12*Assumptions!E$13*Assumptions!E$14)/100000+Revenue!E13+Revenue!E14)*(1-Assumptions!E$25)-'P&L'!E6-'P&L'!E7-'P&L'!E15 -> 93.645224 | C8: =((Assumptions!E$5*Assumptions!E$6*C$3+Assumptions!E$5*Assumptions!E$6*$A8*Assumptions!E$9*Assumptions!E$10*Assumptions!E$11+Assumptions!E$5*Assumptions!E$6*$A8*Assumptions!E$12*Assumptions!E$13*Assumptions!E$14)/100000+Revenue!E13+Revenue!E14)*(1-Assumptions!E$25)-'P&L'!E6-'P&L'!E7-'P&L'!E15 -> 373.00522 | D8: =((Assumptions!E$5*Assumptions!E$6*D$3+Assumptions!E$5*Assumptions!E$6*$A8*Assumptions!E$9*Assumptions!E$10*Assumptions!E$11+Assumptions!E$5*Assumptions!E$6*$A8*Assumptions!E$12*Assumptions!E$13*Assumptions!E$14)/100000+Revenue!E13+Revenue!E14)*(1-Assumptions!E$25)-'P&L'!E6-'P&L'!E7-'P&L'!E15 -> 652.36522 | E8: =((Assumptions!E$5*Assumptions!E$6*E$3+Assumptions!E$5*Assumptions!E$6*$A8*Assumptions!E$9*Assumptions!E$10*Assumptions!E$11+Assumptions!E$5*Assumptions!E$6*$A8*Assumptions!E$12*Assumptions!E$13*Assumptions!E$14)/100000+Revenue!E13+Revenue!E14)*(1-Assumptions!E$25)-'P&L'!E6-'P&L'!E7-'P&L'!E15 -> 931.72522 | F8: =((Assumptions!E$5*Assumptions!E$6*F$3+Assumptions!E$5*Assumptions!E$6*$A8*Assumptions!E$9*Assumptions!E$10*Assumptions!E$11+Assumptions!E$5*Assumptions!E$6*$A8*Assumptions!E$12*Assumptions!E$13*Assumptions!E$14)/100000+Revenue!E13+Revenue!E14)*(1-Assumptions!E$25)-'P&L'!E6-'P&L'!E7-'P&L'!E15 -> 1211.0852
A10: Base case is ₹1,500 and 20%. Every cell recomputes FY29 revenue with that fee and conversion; costs stay at base.
